invideoquiz/__init__.py
invideoquiz/invideoquiz.py
invideoquiz/settings.py
invideoquiz/utils.py
invideoquiz/public/README.txt
invideoquiz/public/css/invideoquiz.css
invideoquiz/public/html/invideoquiz.html
invideoquiz/public/js/src/config.js
invideoquiz/public/js/src/invideoquiz.js
invideoquiz_xblock-1.7.0.dist-info/licenses/LICENSE
invideoquiz_xblock-1.7.0.dist-info/licenses/LICENSE-BSD-3c
invideoquiz_xblock-1.7.0.dist-info/METADATA
invideoquiz_xblock-1.7.0.dist-info/WHEEL
invideoquiz_xblock-1.7.0.dist-info/dependency_links.txt
invideoquiz_xblock-1.7.0.dist-info/entry_points.txt
invideoquiz_xblock-1.7.0.dist-info/top_level.txt
invideoquiz_xblock-1.7.0.dist-info/RECORD
