Metadata-Version: 2.4
Name: invideoquiz-xblock
Version: 1.7.0
Summary: Helper XBlock to locate CAPA problems within videos.
License: AGPL v3
Classifier: Development Status :: 5 - Production/Stable
Classifier: Framework :: Django
Classifier: Framework :: Django :: 4.2
Classifier: Framework :: Django :: 5.2
Classifier: Intended Audience :: Developers
Classifier: License :: OSI Approved :: Apache Software License
Classifier: Natural Language :: English
Classifier: Programming Language :: Python :: 3
Classifier: Programming Language :: Python :: 3.11
Classifier: Programming Language :: Python :: 3.12
License-File: LICENSE
License-File: LICENSE-BSD-3c
Requires-Dist: Django
Requires-Dist: XBlock
Requires-Dist: six
Dynamic: classifier
Dynamic: description
Dynamic: license
Dynamic: license-file
Dynamic: requires-dist
Dynamic: summary
